pkgTest/__init__.py
pkgTest/calculate.py
pkgTest/gui.py
pkgTest/helloworld.py
pkgTest/web.py
pkgTest/test_use/1.txt
pkgTests-0.0.3.dist-info/LICENSE
pkgTests-0.0.3.dist-info/METADATA
pkgTests-0.0.3.dist-info/WHEEL
pkgTests-0.0.3.dist-info/entry_points.txt
pkgTests-0.0.3.dist-info/top_level.txt
pkgTests-0.0.3.dist-info/RECORD
