Metadata-Version: 2.1
Name: pkgTests
Version: 0.0.3
Summary: My first Python Hello world library
Home-page: https://github.com/chenchih/PackageTest
Author: ChenChih.Lee
Author-email: jacklee26@gmail.com
License: MIT
Keywords: python,video,stream,video stream,camera stream,sockets
Platform: UNKNOWN
Classifier: Development Status :: 1 - Planning
Classifier: Intended Audience :: Developers
Classifier: Programming Language :: Python :: 3
Classifier: Operating System :: Unix
Classifier: Operating System :: MacOS :: MacOS X
Classifier: Operating System :: Microsoft :: Windows
License-File: LICENSE
Requires-Dist: selenium
Requires-Dist: webdriver-manager
Requires-Dist: pyautogui
